README.md
setup.py
cbenchmark/__init__.py
cbenchmark/__main__.py
cbenchmark/cli.py
cbenchmark.egg-info/PKG-INFO
cbenchmark.egg-info/SOURCES.txt
cbenchmark.egg-info/dependency_links.txt
cbenchmark.egg-info/entry_points.txt
cbenchmark.egg-info/not-zip-safe
cbenchmark.egg-info/top_level.txt