Metadata-Version: 2.1
Name: cbenchmark
Version: 0.0.1
Summary: cBenchmark
Home-page: UNKNOWN
Author: 
Author-email: 
License: UNKNOWN
Platform: UNKNOWN
